<?xml version="1.0" encoding="UTF-8"?>
<objects serializationModel="Studio.02.03.00">
	<object class="AudioFile" id="{e1ad3af4-d454-4bab-a25f-94fb18b5e1c0}">
		<property name="assetPath">
			<value>gameplay song/melo 2.wav</value>
		</property>
		<property name="isStreaming">
			<value>true</value>
		</property>
		<property name="frequencyInKHz">
			<value>48</value>
		</property>
		<property name="channelCount">
			<value>2</value>
		</property>
		<property name="length">
			<value>44.117666666666665</value>
		</property>
		<relationship name="masterAssetFolder">
			<destination>{7303c168-46fb-49b9-9018-56ef2b93fad1}</destination>
		</relationship>
	</object>
</objects>
